semsis/__init__.py
semsis/kvstore.py
semsis/kvstore_test.py
semsis/registry.py
semsis/registry_test.py
semsis/typing.py
semsis/utils.py
semsis/utils_test.py
semsis/cli/README.rst
semsis/cli/build_retriever.py
semsis/cli/query_interactive.py
semsis/cli/store_kv.py
semsis/encoder/__init__.py
semsis/encoder/sentence_encoder.py
semsis/encoder/sentence_encoder_test.py
semsis/encoder/tokenizer.py
semsis/encoder/tokenizer_test.py
semsis/retriever/__init__.py
semsis/retriever/base.py
semsis/retriever/base_test.py
semsis/retriever/faiss_cpu.py
semsis/retriever/faiss_cpu_test.py
semsis/retriever/faiss_gpu.py
semsis/retriever/faiss_gpu_test.py
semsis-0.1.3.dist-info/METADATA
semsis-0.1.3.dist-info/WHEEL
semsis-0.1.3.dist-info/entry_points.txt
semsis-0.1.3.dist-info/licenses/LICENSE
semsis-0.1.3.dist-info/RECORD
