Metadata-Version: 2.4
Name: semsis
Version: 0.1.3
Summary: A libary for semantic similarity search
Author-email: Hiroyuki Deguchi <deguchi.hiroyuki@nict.go.jp>
License-File: LICENSE
Requires-Python: >=3.9
Requires-Dist: h5py>=3.12.1
Requires-Dist: sentence-transformers>=3.3.1
Requires-Dist: simple-parsing>=0.1.7
Requires-Dist: torch>=2.0.0
Requires-Dist: transformers>=4.47.1
